[{"name":"Merops sp.","date":"2022-01-05","points":13,"tasks":null,"description":"Ameliorated"},
{"name":"Mazama gouazoubira","date":"2022-08-23","points":4,"tasks":null,"description":"middleware"},
{"name":"Phoenicopterus ruber","date":"2022-01-04","points":1,"tasks":null,"description":"Proactive"},
{"name":"Cracticus nigroagularis","date":"2022-02-10","points":1,"tasks":null,"description":"Switchable"},
{"name":"Bucorvus leadbeateri","date":"2021-11-07","points":2,"tasks":null,"description":"Seamless"},
{"name":"Stenella coeruleoalba","date":"2021-12-22","points":2,"tasks":null,"description":"uniform"},
{"name":"Loxodonta africana","date":"2022-03-26","points":12,"tasks":null,"description":"support"},
{"name":"Papio ursinus","date":"2022-08-04","points":9,"tasks":null,"description":"hierarchy"},
{"name":"Hyaena hyaena","date":"2022-05-02","points":1,"tasks":null,"description":"Object-based"},
{"name":"Casmerodius albus","date":"2021-11-11","points":14,"tasks":null,"description":"radical"},
{"name":"Geochelone elephantopus","date":"2022-07-02","points":5,"tasks":null,"description":"disintermediate"},
{"name":"Anser caerulescens","date":"2021-11-04","points":12,"tasks":null,"description":"needs-based"},
{"name":"Anhinga rufa","date":"2022-08-09","points":5,"tasks":null,"description":"Object-based"},
{"name":"Mazama gouazoubira","date":"2021-10-19","points":4,"tasks":null,"description":"Quality-focused"},
{"name":"Trachyphonus vaillantii","date":"2022-07-27","points":10,"tasks":null,"description":"asynchronous"},
{"name":"Hymenolaimus malacorhynchus","date":"2021-10-26","points":2,"tasks":null,"description":"secured line"},
{"name":"Vulpes cinereoargenteus","date":"2022-04-26","points":12,"tasks":null,"description":"definition"},
{"name":"Vulpes chama","date":"2022-06-28","points":2,"tasks":null,"description":"disintermediate"},
{"name":"Ursus maritimus","date":"2022-03-13","points":13,"tasks":null,"description":"Down-sized"},
{"name":"Ciconia episcopus","date":"2022-07-21","points":15,"tasks":null,"description":"fresh-thinking"}]